pyconsole/__init__.py
pyconsole/console.py
code_pyconsole-1.0.1.dist-info/METADATA
code_pyconsole-1.0.1.dist-info/WHEEL
code_pyconsole-1.0.1.dist-info/top_level.txt
code_pyconsole-1.0.1.dist-info/RECORD
