Metadata-Version: 2.2
Name: code-pyconsole
Version: 1.0.1
Summary: A simple console utility for printing messages with color using colorama
Home-page: https://github.com/sikandardeveloper/pyconsole
Author: Sikandar
Author-email: sikandar.dev@gmail.com
Classifier: Development Status :: 3 - Alpha
Classifier: Programming Language :: Python :: 3
Classifier: License :: OSI Approved :: MIT License
Classifier: Operating System :: OS Independent
Requires-Dist: colorama
Dynamic: author
Dynamic: author-email
Dynamic: classifier
Dynamic: description
Dynamic: description-content-type
Dynamic: home-page
Dynamic: requires-dist
Dynamic: summary
